flask_oidc/__init__.py
flask_oidc/discovery.py
flask_oidc/registration.py
flask_oidc/registration_util.py
flask_providers_oidc-1.2.1.dist-info/entry_points.txt
flask_providers_oidc-1.2.1.dist-info/LICENSE.txt
flask_providers_oidc-1.2.1.dist-info/WHEEL
flask_providers_oidc-1.2.1.dist-info/METADATA
flask_providers_oidc-1.2.1.dist-info/RECORD
