Metadata-Version: 2.1
Name: flask-providers-oidc
Version: 1.2.1
Summary: Fork version flask oidc
Author: benbenbang
Author-email: bn@benbenbang.io
Maintainer: benbenbang
Maintainer-email: bn@benbenbang.io
Requires-Python: >=3.7.2,<4.0.0
Classifier: Environment :: Web Environment
Classifier: Framework :: Flask
Classifier: Intended Audience :: Developers
Classifier: License :: OSI Approved :: BSD License
Classifier: Operating System :: OS Independent
Classifier: Programming Language :: Python
Classifier: Programming Language :: Python :: 3
Classifier: Programming Language :: Python :: 3.8
Classifier: Programming Language :: Python :: 3.9
Classifier: Programming Language :: Python :: 3.10
Classifier: Programming Language :: Python :: 3.11
Classifier: Programming Language :: Python :: 3
Classifier: Programming Language :: Python :: 3.10
Classifier: Programming Language :: Python :: 3.11
Classifier: Programming Language :: Python :: 3.7
Classifier: Programming Language :: Python :: 3.8
Classifier: Programming Language :: Python :: 3.9
Classifier: Topic :: Internet :: WWW/HTTP :: Dynamic Content
Classifier: Topic :: Software Development :: Libraries :: Python Modules
Requires-Dist: PyJWT (>=2.6.0,<3.0.0)
Requires-Dist: oauth2client (>=4.1.3,<5.0.0)
